plugnparse/__init__.py
plugnparse/equal.py
plugnparse/io.py
plugnparse/logger.py
plugnparse/numerics.py
plugnparse/parameters.py
plugnparse/parsable.py
plugnparse/plugin.py
plugnparse/properties.py
plugnparse/py.typed
plugnparse-0.2.2.data/data/README.md
plugnparse-0.2.2.data/data/requirements.txt
plugnparse-0.2.2.dist-info/licenses/LICENSE
plugnparse-0.2.2.dist-info/METADATA
plugnparse-0.2.2.dist-info/WHEEL
plugnparse-0.2.2.dist-info/top_level.txt
plugnparse-0.2.2.dist-info/RECORD
