Metadata-Version: 2.4
Name: plugnparse
Version: 0.2.2
Summary: Python utilities package for plugin style architectures with parsable classes for parameters.
Author: Dylan DeSantis
Maintainer: Dylan DeSantis
License:                                  Apache License
Project-URL: Homepage, https://github.com/orthly/DDDeSantis/plugnparse
Project-URL: Bug Reports, https://github.com/orthly/DDDeSantis/plugnparse
Project-URL: Source, https://github.com/orthly/DDDeSantis/plugnparse
Keywords: plugin,parsing,json
Classifier: Development Status :: 3 - Alpha
Classifier: Intended Audience :: Developers
Classifier: License :: OSI Approved :: MIT License
Classifier: Programming Language :: Python :: 3
Classifier: Programming Language :: Python :: 3.8
Classifier: Programming Language :: Python :: 3.9
Classifier: Programming Language :: Python :: 3.10
Classifier: Programming Language :: Python :: 3.11
Classifier: Programming Language :: Python :: 3.12
Classifier: Programming Language :: Python :: 3 :: Only
Requires-Python: >=3.8
License-File: LICENSE
Requires-Dist: typing
Requires-Dist: numpy
Requires-Dist: datetime
Provides-Extra: test
Requires-Dist: pytest; extra == "test"
Requires-Dist: coverage; extra == "test"
Requires-Dist: pyfakefs; extra == "test"
Requires-Dist: mock; extra == "test"
Dynamic: license-file
